programengineergpt/__init__.py
programengineergpt/__main__.py
programengineergpt/config.py
programengineergpt/main.py
programengineergpt/program_engineer.py
pgpt-0.0.5.dist-info/LICENSE
pgpt-0.0.5.dist-info/METADATA
pgpt-0.0.5.dist-info/WHEEL
pgpt-0.0.5.dist-info/entry_points.txt
pgpt-0.0.5.dist-info/top_level.txt
pgpt-0.0.5.dist-info/RECORD
