Metadata-Version: 2.1
Name: pgpt
Version: 0.0.5
Summary: ProgramEngineerGPT is an interactive command line tool that leverages the power of AI to assist developers with code comprehension, exploration, and generation. It serves as a virtual assistant that can analyze codebases, answer queries about code, and even help in setting up new coding projects.
Author-email: Brette Geary <hackedbg@outlook.com>
Project-URL: Homepage, https://github.com/hackedbyagirl/programengineergpt
Project-URL: Bug Tracker, https://github.com/hackedbyagirl/programengineergpt/issues
Requires-Python: >=3.10
License-File: LICENSE
Requires-Dist: aioboto3 (==11.2.0)
Requires-Dist: aiobotocore (==2.5.0)
Requires-Dist: aiohttp (==3.8.4)
Requires-Dist: aioitertools (==0.11.0)
Requires-Dist: aiosignal (==1.3.1)
Requires-Dist: async-timeout (==4.0.2)
Requires-Dist: attrs (==23.1.0)
Requires-Dist: black (==23.3.0)
Requires-Dist: boto3 (==1.26.76)
Requires-Dist: botocore (==1.29.76)
Requires-Dist: certifi (==2023.5.7)
Requires-Dist: charset-normalizer (==3.1.0)
Requires-Dist: click (==8.1.3)
Requires-Dist: colored (==2.1.1)
Requires-Dist: dataclasses-json (==0.5.8)
Requires-Dist: deeplake (==3.6.6)
Requires-Dist: dill (==0.3.6)
Requires-Dist: entrypoints (==0.4)
Requires-Dist: exceptiongroup (==1.1.1)
Requires-Dist: frozenlist (==1.3.3)
Requires-Dist: greenlet (==2.0.2)
Requires-Dist: humbug (==0.3.1)
Requires-Dist: idna (==3.4)
Requires-Dist: iniconfig (==2.0.0)
Requires-Dist: isort (==5.12.0)
Requires-Dist: jmespath (==1.0.1)
Requires-Dist: langchain (==0.0.212)
Requires-Dist: langchainplus-sdk (==0.0.17)
Requires-Dist: marshmallow (==3.19.0)
Requires-Dist: marshmallow-enum (==1.5.1)
Requires-Dist: multidict (==6.0.4)
Requires-Dist: multiprocess (==0.70.14)
Requires-Dist: mypy-extensions (==1.0.0)
Requires-Dist: nest-asyncio (==1.5.6)
Requires-Dist: numcodecs (==0.11.0)
Requires-Dist: numexpr (==2.8.4)
Requires-Dist: numpy (==1.25.0)
Requires-Dist: openai (==0.27.8)
Requires-Dist: openapi-schema-pydantic (==1.2.4)
Requires-Dist: packaging (==23.1)
Requires-Dist: pathos (==0.3.0)
Requires-Dist: pathspec (==0.11.1)
Requires-Dist: Pillow (==9.5.0)
Requires-Dist: platformdirs (==3.8.0)
Requires-Dist: pluggy (==1.2.0)
Requires-Dist: pox (==0.3.2)
Requires-Dist: ppft (==1.7.6.6)
Requires-Dist: prompt-toolkit (==3.0.38)
Requires-Dist: pydantic (==1.10.9)
Requires-Dist: PyJWT (==2.7.0)
Requires-Dist: pytest (==7.4.0)
Requires-Dist: python-dateutil (==2.8.2)
Requires-Dist: python-dotenv (==1.0.0)
Requires-Dist: PyYAML (==6.0)
Requires-Dist: questionary (==1.10.0)
Requires-Dist: regex (==2023.6.3)
Requires-Dist: requests (==2.31.0)
Requires-Dist: ruff (==0.0.275)
Requires-Dist: s3transfer (==0.6.1)
Requires-Dist: six (==1.16.0)
Requires-Dist: SQLAlchemy (==2.0.17)
Requires-Dist: tenacity (==8.2.2)
Requires-Dist: tiktoken (==0.4.0)
Requires-Dist: tomli (==2.0.1)
Requires-Dist: tqdm (==4.65.0)
Requires-Dist: typing-inspect (==0.9.0)
Requires-Dist: typing-extensions (==4.6.3)
Requires-Dist: urllib3 (==1.26.16)
Requires-Dist: wcwidth (==0.2.6)
Requires-Dist: wrapt (==1.15.0)
Requires-Dist: yarl (==1.9.2)
